LICENSE
pymcfunction/__init__.py
pymcfunction/cli.py
pymcfunction/commands/bossbar.py
pymcfunction/commands/effect.py
pymcfunction/commands/execute.py
pymcfunction/commands/experience.py
pymcfunction/commands/item.py
pymcfunction/commands/scoreboard.py
pymcfunction/commands/simple.py
pymcfunction/commands/tag.py
pymcfunction/commands/team.py
pymcfunction/commands/teleport.py
pymcfunction/commands/time.py
pymcfunction/types.py
pymcfunction/update_specific_types/advancement.py
pymcfunction/update_specific_types/block.py
pymcfunction/update_specific_types/effect.py
pymcfunction/update_specific_types/entity.py
pymcfunction/update_specific_types/item.py
pymcfunction/util.py
pymcfunction-0.1.6.dist-info/entry_points.txt
pymcfunction-0.1.6.dist-info/LICENSE
pymcfunction-0.1.6.dist-info/WHEEL
pymcfunction-0.1.6.dist-info/METADATA
pymcfunction-0.1.6.dist-info/RECORD
