Metadata-Version: 2.1
Name: pymcfunction
Version: 0.1.6
Summary: PyMCFunction is a tool to write Minecraft datapacks in Python.
Home-page: https://github.com/PaddeCraft/PyMCFunction
Keywords: python,minecraft,toml,cli
Author: PaddeCraft
Author-email: paddecraft@gmail.com
Requires-Python: >=3.10,<4.0
Classifier: Programming Language :: Python :: 3
Classifier: Programming Language :: Python :: 3.10
Classifier: Programming Language :: Python :: 3.11
Requires-Dist: toml (>=0.10.2,<0.11.0)
Requires-Dist: typer (>=0.6.1,<0.7.0)
Project-URL: Repository, https://github.com/PaddeCraft/PyMCFunction
